{
  "best_metric": null,
  "best_model_checkpoint": null,
  "epoch": 9.6,
  "eval_steps": 500,
  "global_step": 150,
  "is_hyper_param_search": false,
  "is_local_process_zero": true,
  "is_world_process_zero": true,
  "log_history": [
    {
      "epoch": 0.06,
      "learning_rate": 0.0,
      "loss": 1.5776,
      "step": 1
    },
    {
      "epoch": 0.13,
      "learning_rate": 1e-05,
      "loss": 1.4576,
      "step": 2
    },
    {
      "epoch": 0.19,
      "learning_rate": 1e-05,
      "loss": 1.3377,
      "step": 3
    },
    {
      "epoch": 0.26,
      "learning_rate": 1e-05,
      "loss": 1.3992,
      "step": 4
    },
    {
      "epoch": 0.32,
      "learning_rate": 1e-05,
      "loss": 1.3871,
      "step": 5
    },
    {
      "epoch": 0.38,
      "learning_rate": 1e-05,
      "loss": 1.315,
      "step": 6
    },
    {
      "epoch": 0.45,
      "learning_rate": 1e-05,
      "loss": 1.2542,
      "step": 7
    },
    {
      "epoch": 0.51,
      "learning_rate": 1e-05,
      "loss": 1.1883,
      "step": 8
    },
    {
      "epoch": 0.58,
      "learning_rate": 1e-05,
      "loss": 1.1681,
      "step": 9
    },
    {
      "epoch": 0.64,
      "learning_rate": 1e-05,
      "loss": 1.0891,
      "step": 10
    },
    {
      "epoch": 0.7,
      "learning_rate": 1e-05,
      "loss": 1.0182,
      "step": 11
    },
    {
      "epoch": 0.77,
      "learning_rate": 1e-05,
      "loss": 0.939,
      "step": 12
    },
    {
      "epoch": 0.83,
      "learning_rate": 1e-05,
      "loss": 0.8938,
      "step": 13
    },
    {
      "epoch": 0.9,
      "learning_rate": 1e-05,
      "loss": 0.938,
      "step": 14
    },
    {
      "epoch": 0.96,
      "learning_rate": 1e-05,
      "loss": 0.8699,
      "step": 15
    },
    {
      "epoch": 1.02,
      "learning_rate": 1e-05,
      "loss": 0.9118,
      "step": 16
    },
    {
      "epoch": 1.09,
      "learning_rate": 1e-05,
      "loss": 0.9101,
      "step": 17
    },
    {
      "epoch": 1.15,
      "learning_rate": 1e-05,
      "loss": 0.7326,
      "step": 18
    },
    {
      "epoch": 1.22,
      "learning_rate": 1e-05,
      "loss": 0.6741,
      "step": 19
    },
    {
      "epoch": 1.28,
      "learning_rate": 1e-05,
      "loss": 0.7126,
      "step": 20
    },
    {
      "epoch": 1.34,
      "learning_rate": 1e-05,
      "loss": 0.7938,
      "step": 21
    },
    {
      "epoch": 1.41,
      "learning_rate": 1e-05,
      "loss": 0.6988,
      "step": 22
    },
    {
      "epoch": 1.47,
      "learning_rate": 1e-05,
      "loss": 0.6578,
      "step": 23
    },
    {
      "epoch": 1.54,
      "learning_rate": 1e-05,
      "loss": 0.7528,
      "step": 24
    },
    {
      "epoch": 1.6,
      "learning_rate": 1e-05,
      "loss": 0.7137,
      "step": 25
    },
    {
      "epoch": 1.66,
      "learning_rate": 1e-05,
      "loss": 0.6711,
      "step": 26
    },
    {
      "epoch": 1.73,
      "learning_rate": 1e-05,
      "loss": 0.6093,
      "step": 27
    },
    {
      "epoch": 1.79,
      "learning_rate": 1e-05,
      "loss": 0.6704,
      "step": 28
    },
    {
      "epoch": 1.86,
      "learning_rate": 1e-05,
      "loss": 0.6022,
      "step": 29
    },
    {
      "epoch": 1.92,
      "learning_rate": 1e-05,
      "loss": 0.651,
      "step": 30
    },
    {
      "epoch": 1.98,
      "learning_rate": 1e-05,
      "loss": 0.6435,
      "step": 31
    },
    {
      "epoch": 2.05,
      "learning_rate": 1e-05,
      "loss": 0.6675,
      "step": 32
    },
    {
      "epoch": 2.11,
      "learning_rate": 1e-05,
      "loss": 0.6303,
      "step": 33
    },
    {
      "epoch": 2.18,
      "learning_rate": 1e-05,
      "loss": 0.5193,
      "step": 34
    },
    {
      "epoch": 2.24,
      "learning_rate": 1e-05,
      "loss": 0.5373,
      "step": 35
    },
    {
      "epoch": 2.3,
      "learning_rate": 1e-05,
      "loss": 0.5557,
      "step": 36
    },
    {
      "epoch": 2.37,
      "learning_rate": 1e-05,
      "loss": 0.5567,
      "step": 37
    },
    {
      "epoch": 2.43,
      "learning_rate": 1e-05,
      "loss": 0.5857,
      "step": 38
    },
    {
      "epoch": 2.5,
      "learning_rate": 1e-05,
      "loss": 0.5054,
      "step": 39
    },
    {
      "epoch": 2.56,
      "learning_rate": 1e-05,
      "loss": 0.588,
      "step": 40
    },
    {
      "epoch": 2.62,
      "learning_rate": 1e-05,
      "loss": 0.5292,
      "step": 41
    },
    {
      "epoch": 2.69,
      "learning_rate": 1e-05,
      "loss": 0.5027,
      "step": 42
    },
    {
      "epoch": 2.75,
      "learning_rate": 1e-05,
      "loss": 0.4709,
      "step": 43
    },
    {
      "epoch": 2.82,
      "learning_rate": 1e-05,
      "loss": 0.4775,
      "step": 44
    },
    {
      "epoch": 2.88,
      "learning_rate": 1e-05,
      "loss": 0.4524,
      "step": 45
    },
    {
      "epoch": 2.94,
      "learning_rate": 1e-05,
      "loss": 0.4743,
      "step": 46
    },
    {
      "epoch": 3.01,
      "learning_rate": 1e-05,
      "loss": 0.5164,
      "step": 47
    },
    {
      "epoch": 3.07,
      "learning_rate": 1e-05,
      "loss": 0.5186,
      "step": 48
    },
    {
      "epoch": 3.14,
      "learning_rate": 1e-05,
      "loss": 0.4272,
      "step": 49
    },
    {
      "epoch": 3.2,
      "learning_rate": 1e-05,
      "loss": 0.3765,
      "step": 50
    },
    {
      "epoch": 3.26,
      "learning_rate": 1e-05,
      "loss": 0.42,
      "step": 51
    },
    {
      "epoch": 3.33,
      "learning_rate": 1e-05,
      "loss": 0.4258,
      "step": 52
    },
    {
      "epoch": 3.39,
      "learning_rate": 1e-05,
      "loss": 0.4376,
      "step": 53
    },
    {
      "epoch": 3.46,
      "learning_rate": 1e-05,
      "loss": 0.4181,
      "step": 54
    },
    {
      "epoch": 3.52,
      "learning_rate": 1e-05,
      "loss": 0.437,
      "step": 55
    },
    {
      "epoch": 3.58,
      "learning_rate": 1e-05,
      "loss": 0.441,
      "step": 56
    },
    {
      "epoch": 3.65,
      "learning_rate": 1e-05,
      "loss": 0.3629,
      "step": 57
    },
    {
      "epoch": 3.71,
      "learning_rate": 1e-05,
      "loss": 0.4047,
      "step": 58
    },
    {
      "epoch": 3.78,
      "learning_rate": 1e-05,
      "loss": 0.3718,
      "step": 59
    },
    {
      "epoch": 3.84,
      "learning_rate": 1e-05,
      "loss": 0.344,
      "step": 60
    },
    {
      "epoch": 3.9,
      "learning_rate": 1e-05,
      "loss": 0.41,
      "step": 61
    },
    {
      "epoch": 3.97,
      "learning_rate": 1e-05,
      "loss": 0.3602,
      "step": 62
    },
    {
      "epoch": 4.03,
      "learning_rate": 1e-05,
      "loss": 0.3843,
      "step": 63
    },
    {
      "epoch": 4.1,
      "learning_rate": 1e-05,
      "loss": 0.3825,
      "step": 64
    },
    {
      "epoch": 4.16,
      "learning_rate": 1e-05,
      "loss": 0.3236,
      "step": 65
    },
    {
      "epoch": 4.22,
      "learning_rate": 1e-05,
      "loss": 0.2965,
      "step": 66
    },
    {
      "epoch": 4.29,
      "learning_rate": 1e-05,
      "loss": 0.3134,
      "step": 67
    },
    {
      "epoch": 4.35,
      "learning_rate": 1e-05,
      "loss": 0.3849,
      "step": 68
    },
    {
      "epoch": 4.42,
      "learning_rate": 1e-05,
      "loss": 0.3685,
      "step": 69
    },
    {
      "epoch": 4.48,
      "learning_rate": 1e-05,
      "loss": 0.3231,
      "step": 70
    },
    {
      "epoch": 4.54,
      "learning_rate": 1e-05,
      "loss": 0.3592,
      "step": 71
    },
    {
      "epoch": 4.61,
      "learning_rate": 1e-05,
      "loss": 0.3377,
      "step": 72
    },
    {
      "epoch": 4.67,
      "learning_rate": 1e-05,
      "loss": 0.3131,
      "step": 73
    },
    {
      "epoch": 4.74,
      "learning_rate": 1e-05,
      "loss": 0.321,
      "step": 74
    },
    {
      "epoch": 4.8,
      "learning_rate": 1e-05,
      "loss": 0.3083,
      "step": 75
    },
    {
      "epoch": 4.86,
      "learning_rate": 1e-05,
      "loss": 0.2973,
      "step": 76
    },
    {
      "epoch": 4.93,
      "learning_rate": 1e-05,
      "loss": 0.3393,
      "step": 77
    },
    {
      "epoch": 4.99,
      "learning_rate": 1e-05,
      "loss": 0.2844,
      "step": 78
    },
    {
      "epoch": 5.06,
      "learning_rate": 1e-05,
      "loss": 0.3126,
      "step": 79
    },
    {
      "epoch": 5.12,
      "learning_rate": 1e-05,
      "loss": 0.2954,
      "step": 80
    },
    {
      "epoch": 5.18,
      "learning_rate": 1e-05,
      "loss": 0.2679,
      "step": 81
    },
    {
      "epoch": 5.25,
      "learning_rate": 1e-05,
      "loss": 0.2621,
      "step": 82
    },
    {
      "epoch": 5.31,
      "learning_rate": 1e-05,
      "loss": 0.2999,
      "step": 83
    },
    {
      "epoch": 5.38,
      "learning_rate": 1e-05,
      "loss": 0.3083,
      "step": 84
    },
    {
      "epoch": 5.44,
      "learning_rate": 1e-05,
      "loss": 0.3178,
      "step": 85
    },
    {
      "epoch": 5.5,
      "learning_rate": 1e-05,
      "loss": 0.272,
      "step": 86
    },
    {
      "epoch": 5.57,
      "learning_rate": 1e-05,
      "loss": 0.3361,
      "step": 87
    },
    {
      "epoch": 5.63,
      "learning_rate": 1e-05,
      "loss": 0.2868,
      "step": 88
    },
    {
      "epoch": 5.7,
      "learning_rate": 1e-05,
      "loss": 0.275,
      "step": 89
    },
    {
      "epoch": 5.76,
      "learning_rate": 1e-05,
      "loss": 0.2661,
      "step": 90
    },
    {
      "epoch": 5.82,
      "learning_rate": 1e-05,
      "loss": 0.2578,
      "step": 91
    },
    {
      "epoch": 5.89,
      "learning_rate": 1e-05,
      "loss": 0.2628,
      "step": 92
    },
    {
      "epoch": 5.95,
      "learning_rate": 1e-05,
      "loss": 0.2466,
      "step": 93
    },
    {
      "epoch": 6.02,
      "learning_rate": 1e-05,
      "loss": 0.23,
      "step": 94
    },
    {
      "epoch": 6.08,
      "learning_rate": 1e-05,
      "loss": 0.2563,
      "step": 95
    },
    {
      "epoch": 6.14,
      "learning_rate": 1e-05,
      "loss": 0.2731,
      "step": 96
    },
    {
      "epoch": 6.21,
      "learning_rate": 1e-05,
      "loss": 0.2276,
      "step": 97
    },
    {
      "epoch": 6.27,
      "learning_rate": 1e-05,
      "loss": 0.2344,
      "step": 98
    },
    {
      "epoch": 6.34,
      "learning_rate": 1e-05,
      "loss": 0.2461,
      "step": 99
    },
    {
      "epoch": 6.4,
      "learning_rate": 1e-05,
      "loss": 0.3181,
      "step": 100
    },
    {
      "epoch": 6.46,
      "learning_rate": 1e-05,
      "loss": 0.234,
      "step": 101
    },
    {
      "epoch": 6.53,
      "learning_rate": 1e-05,
      "loss": 0.2846,
      "step": 102
    },
    {
      "epoch": 6.59,
      "learning_rate": 1e-05,
      "loss": 0.2809,
      "step": 103
    },
    {
      "epoch": 6.66,
      "learning_rate": 1e-05,
      "loss": 0.2391,
      "step": 104
    },
    {
      "epoch": 6.72,
      "learning_rate": 1e-05,
      "loss": 0.2395,
      "step": 105
    },
    {
      "epoch": 6.78,
      "learning_rate": 1e-05,
      "loss": 0.2283,
      "step": 106
    },
    {
      "epoch": 6.85,
      "learning_rate": 1e-05,
      "loss": 0.2203,
      "step": 107
    },
    {
      "epoch": 6.91,
      "learning_rate": 1e-05,
      "loss": 0.2547,
      "step": 108
    },
    {
      "epoch": 6.98,
      "learning_rate": 1e-05,
      "loss": 0.1823,
      "step": 109
    },
    {
      "epoch": 7.04,
      "learning_rate": 1e-05,
      "loss": 0.2125,
      "step": 110
    },
    {
      "epoch": 7.1,
      "learning_rate": 1e-05,
      "loss": 0.2542,
      "step": 111
    },
    {
      "epoch": 7.17,
      "learning_rate": 1e-05,
      "loss": 0.2185,
      "step": 112
    },
    {
      "epoch": 7.23,
      "learning_rate": 1e-05,
      "loss": 0.209,
      "step": 113
    },
    {
      "epoch": 7.3,
      "learning_rate": 1e-05,
      "loss": 0.2337,
      "step": 114
    },
    {
      "epoch": 7.36,
      "learning_rate": 1e-05,
      "loss": 0.2381,
      "step": 115
    },
    {
      "epoch": 7.42,
      "learning_rate": 1e-05,
      "loss": 0.2785,
      "step": 116
    },
    {
      "epoch": 7.49,
      "learning_rate": 1e-05,
      "loss": 0.2086,
      "step": 117
    },
    {
      "epoch": 7.55,
      "learning_rate": 1e-05,
      "loss": 0.284,
      "step": 118
    },
    {
      "epoch": 7.62,
      "learning_rate": 1e-05,
      "loss": 0.256,
      "step": 119
    },
    {
      "epoch": 7.68,
      "learning_rate": 1e-05,
      "loss": 0.206,
      "step": 120
    },
    {
      "epoch": 7.74,
      "learning_rate": 1e-05,
      "loss": 0.2347,
      "step": 121
    },
    {
      "epoch": 7.81,
      "learning_rate": 1e-05,
      "loss": 0.1828,
      "step": 122
    },
    {
      "epoch": 7.87,
      "learning_rate": 1e-05,
      "loss": 0.2061,
      "step": 123
    },
    {
      "epoch": 7.94,
      "learning_rate": 1e-05,
      "loss": 0.2231,
      "step": 124
    },
    {
      "epoch": 8.0,
      "learning_rate": 1e-05,
      "loss": 0.1854,
      "step": 125
    },
    {
      "epoch": 8.06,
      "learning_rate": 1e-05,
      "loss": 0.2032,
      "step": 126
    },
    {
      "epoch": 8.13,
      "learning_rate": 1e-05,
      "loss": 0.2171,
      "step": 127
    },
    {
      "epoch": 8.19,
      "learning_rate": 1e-05,
      "loss": 0.1799,
      "step": 128
    },
    {
      "epoch": 8.26,
      "learning_rate": 1e-05,
      "loss": 0.233,
      "step": 129
    },
    {
      "epoch": 8.32,
      "learning_rate": 1e-05,
      "loss": 0.1904,
      "step": 130
    },
    {
      "epoch": 8.38,
      "learning_rate": 1e-05,
      "loss": 0.2558,
      "step": 131
    },
    {
      "epoch": 8.45,
      "learning_rate": 1e-05,
      "loss": 0.2254,
      "step": 132
    },
    {
      "epoch": 8.51,
      "learning_rate": 1e-05,
      "loss": 0.2276,
      "step": 133
    },
    {
      "epoch": 8.58,
      "learning_rate": 1e-05,
      "loss": 0.2433,
      "step": 134
    },
    {
      "epoch": 8.64,
      "learning_rate": 1e-05,
      "loss": 0.2196,
      "step": 135
    },
    {
      "epoch": 8.7,
      "learning_rate": 1e-05,
      "loss": 0.2033,
      "step": 136
    },
    {
      "epoch": 8.77,
      "learning_rate": 1e-05,
      "loss": 0.2031,
      "step": 137
    },
    {
      "epoch": 8.83,
      "learning_rate": 1e-05,
      "loss": 0.1833,
      "step": 138
    },
    {
      "epoch": 8.9,
      "learning_rate": 1e-05,
      "loss": 0.2178,
      "step": 139
    },
    {
      "epoch": 8.96,
      "learning_rate": 1e-05,
      "loss": 0.1671,
      "step": 140
    },
    {
      "epoch": 9.02,
      "learning_rate": 1e-05,
      "loss": 0.173,
      "step": 141
    },
    {
      "epoch": 9.09,
      "learning_rate": 1e-05,
      "loss": 0.208,
      "step": 142
    },
    {
      "epoch": 9.15,
      "learning_rate": 1e-05,
      "loss": 0.209,
      "step": 143
    },
    {
      "epoch": 9.22,
      "learning_rate": 1e-05,
      "loss": 0.1707,
      "step": 144
    },
    {
      "epoch": 9.28,
      "learning_rate": 1e-05,
      "loss": 0.1846,
      "step": 145
    },
    {
      "epoch": 9.34,
      "learning_rate": 1e-05,
      "loss": 0.2252,
      "step": 146
    },
    {
      "epoch": 9.41,
      "learning_rate": 1e-05,
      "loss": 0.211,
      "step": 147
    },
    {
      "epoch": 9.47,
      "learning_rate": 1e-05,
      "loss": 0.188,
      "step": 148
    },
    {
      "epoch": 9.54,
      "learning_rate": 1e-05,
      "loss": 0.2246,
      "step": 149
    },
    {
      "epoch": 9.6,
      "learning_rate": 1e-05,
      "loss": 0.2468,
      "step": 150
    },
    {
      "epoch": 9.6,
      "step": 150,
      "total_flos": 1.0790007698620416e+18,
      "train_loss": 0.44238926033178966,
      "train_runtime": 2804.682,
      "train_samples_per_second": 3.565,
      "train_steps_per_second": 0.053
    }
  ],
  "logging_steps": 1.0,
  "max_steps": 150,
  "num_train_epochs": 10,
  "save_steps": 1000,
  "total_flos": 1.0790007698620416e+18,
  "trial_name": null,
  "trial_params": null
}
